Metadata-Version: 2.1
Name: robotframework-parrot-audio
Version: 1.0.1
Summary: Audio controller to play, record audio file and convert audio formats
Home-page: https://github.com/zilogic-systems/parrot
Author: Zilogic Systems
Author-email: code@zilogic.com
Classifier: Programming Language :: Python :: 3
Requires-Python: >=3.6
License-File: LICENSE
Requires-Dist: pyaudio
Requires-Dist: pydub
Requires-Dist: robotframework
